COPYING
MANIFEST.in
_hesiod.pyx
hesiod.py
setup.py
PyHesiod.egg-info/PKG-INFO
PyHesiod.egg-info/SOURCES.txt
PyHesiod.egg-info/dependency_links.txt
PyHesiod.egg-info/top_level.txt