Metadata-Version: 1.1
Name: PyHesiod
Version: 0.2.10
Summary: PyHesiod - Python bindings for the Heisod naming library
Home-page: http://ebroder.net/code/PyHesiod
Author: Evan Broder
Author-email: broder@mit.edu
License: MIT
Platform: UNKNOWN
Requires: Pyrex
